atml/__init__.py
atml/controller/__init__.py
atml/controller/auto_deploy_socket.py
atml/controller/auto_feature_socket.py
atml/controller/auto_learning_socket.py
atml/controller/base_socket.py
atml/controller/controller.py
atml/controller/local_server.py
atml/tuner/__init__.py
atml/tuner/atml_impl.py
atml/tuner/executor.py
atml/tuner/model_repo_manager.py
atml/tuner/nni_exec_manager.py
atml/tuner/config/default_models.yml
atml/tuner/config/default_nni_exec.yml
atml/tuner/config/nni_template.yml
atml/tuner/db/__init__.py
atml/tuner/db/model_dao.py
atml/tuner/db/model_db.py
atml/util/__init__.py
atml/util/atm_util.py
atml-0.0.1.dist-info/METADATA
atml-0.0.1.dist-info/WHEEL
atml-0.0.1.dist-info/top_level.txt
atml-0.0.1.dist-info/RECORD
