Metadata-Version: 2.1
Name: atml
Version: 0.0.1
Summary: Automation Toolkit for Machine Learning
Home-page: https://github.com/ahhuisg/atml
Author: ahhuisg
Author-email: yanhui79@gmail.com
License: UNKNOWN
Platform: UNKNOWN
Requires-Dist: nni (==1.6)
Requires-Dist: numpy (==1.18.4)
Requires-Dist: PyYaml (==5.3.1)
Requires-Dist: pandas (==1.0.3)
Requires-Dist: xgboost (==1.1.1)
Requires-Dist: logzero (==1.5.0)
Requires-Dist: Flask (==1.1.2)
